gsmote/__init__.py
gsmote/geometric_smote.py
gsmote/py.typed
geometric_smote-0.2.3.dist-info/WHEEL
geometric_smote-0.2.3.dist-info/METADATA
geometric_smote-0.2.3.dist-info/licenses/LICENSE
geometric_smote-0.2.3.dist-info/RECORD
