Metadata-Version: 2.1
Name: geometric-smote
Version: 0.2.3
Summary: Implementation of the Geometric SMOTE algorithm, a geometrically enhanced drop-in replacement for SMOTE. It is compatible with scikit-learn and imbalanced-learn.
License: MIT
Author-email: Georgios Douzas <gdouzas@icloud.com>
Requires-Python: >=3.10, <3.12
Classifier: Development Status :: 4 - Beta
Classifier: Intended Audience :: Developers
Classifier: Programming Language :: Python
Classifier: Programming Language :: Python :: 3
Classifier: Programming Language :: Python :: 3 :: Only
Classifier: Programming Language :: Python :: 3.10
Classifier: Programming Language :: Python :: 3.11
Classifier: Topic :: Documentation
Classifier: Topic :: Software Development
Classifier: Topic :: Utilities
Classifier: Typing :: Typed
Requires-Dist: imbalanced-learn>=0.11.0
Requires-Dist: scikit-learn>=1.3.2
Requires-Dist: typing-extensions>=4.8.0
Project-URL: Changelog, https://georgedouzas.github.io/geometric-smote/changelog
Project-URL: Discussions, https://github.com/georgedouzas/geometric-smote/discussions
Project-URL: Documentation, https://georgedouzas.github.io/geometric-smote
Project-URL: Funding, https://github.com/sponsors/georgedouzas
Project-URL: Gitter, https://gitter.im/geometric-smote/community
Project-URL: Homepage, https://georgedouzas.github.io/geometric-smote
Project-URL: Issues, https://github.com/georgedouzas/geometric-smote/issues
Project-URL: Repository, https://github.com/georgedouzas/geometric-smote
